nfiniity_utils/__init__.py
nfiniity_utils/signal.py
nfiniity_utils/timer.py
test/__init__.py
test/test_timer.py
nfiniity_utils-0.0.6.dist-info/LICENSE
nfiniity_utils-0.0.6.dist-info/METADATA
nfiniity_utils-0.0.6.dist-info/WHEEL
nfiniity_utils-0.0.6.dist-info/top_level.txt
nfiniity_utils-0.0.6.dist-info/RECORD
