Metadata-Version: 2.1
Name: nfiniity-utils
Version: 0.0.6
Summary: Diverse python utilities by nfiniity GmbH
Home-page: https://github.com/apgeorg/nfiniity_utils.git
Author: Apostolos Georgiadis
Author-email: apostolos.georgiadis@nfiniity.com
License: UNKNOWN
Platform: UNKNOWN
Classifier: Development Status :: 3 - Alpha
Classifier: Intended Audience :: Developers
Classifier: Topic :: Software Development :: Build Tools
Classifier: Programming Language :: Python :: 3
Classifier: License :: OSI Approved :: MIT License
Classifier: Operating System :: OS Independent
